zerionAPI/__init__.py
zerionAPI/api.py
zerionAPI/dfa.py
zerionAPI/dfa_utilities.py
zerionAPI/ifb.py
zerionAPI/ifb_utilities.py
zerionAPI-0.0.4.dist-info/LICENSE
zerionAPI-0.0.4.dist-info/METADATA
zerionAPI-0.0.4.dist-info/WHEEL
zerionAPI-0.0.4.dist-info/top_level.txt
zerionAPI-0.0.4.dist-info/RECORD
