Metadata-Version: 2.1
Name: zerionAPI
Version: 0.0.4
Summary: Zerion Software API Wrapper
Home-page: https://github.com/jhsu98/zerion-py
Author: Jonathan Hsu
Author-email: jhsu98@gmail.com
License: MIT
Platform: UNKNOWN
Requires-Python: >=3.0
License-File: LICENSE
Requires-Dist: pyjwt
Requires-Dist: requests
Requires-Dist: pytest
